nbsstorytime/__init__.py
nbsstorytime/_modidx.py
nbsstorytime/core.py
nbsstorytime-0.0.8.dist-info/licenses/LICENSE
nbsstorytime-0.0.8.dist-info/METADATA
nbsstorytime-0.0.8.dist-info/WHEEL
nbsstorytime-0.0.8.dist-info/entry_points.txt
nbsstorytime-0.0.8.dist-info/top_level.txt
nbsstorytime-0.0.8.dist-info/RECORD
