Metadata-Version: 2.4
Name: nbsstorytime
Version: 0.0.8
Summary: Python Library to write N4L notes from Jupyter Notebooks
Home-page: https://github.com/chrphb/nbsstorytime
Author: Christophe Beauce
Author-email: chris@chrphb.com
License: Apache Software License 2.0
Keywords: nbdev jupyter notebook python
Classifier: Development Status :: 4 - Beta
Classifier: Intended Audience :: Developers
Classifier: Natural Language :: English
Classifier: Programming Language :: Python :: 3.10
Classifier: Programming Language :: Python :: 3.11
Classifier: Programming Language :: Python :: 3.12
Classifier: License :: OSI Approved :: Apache Software License
Requires-Python: >=3.10
License-File: LICENSE
Requires-Dist: fastcore==1.9.5
Requires-Dist: nbformat==5.10.4
Requires-Dist: ipykernel==6.31.0
Provides-Extra: dev
Requires-Dist: nbdev==2.4.7; extra == "dev"
Dynamic: author
Dynamic: author-email
Dynamic: classifier
Dynamic: description
Dynamic: description-content-type
Dynamic: home-page
Dynamic: keywords
Dynamic: license
Dynamic: license-file
Dynamic: provides-extra
Dynamic: requires-dist
Dynamic: requires-python
Dynamic: summary
